movva_salesforce_tools/__init__.py
movva_salesforce_tools/salesforce/__init__.py
movva_salesforce_tools/salesforce/database/__init__.py
movva_salesforce_tools/salesforce/database/firestore.py
movva_salesforce_tools/salesforce/marketing_cloud/__init__.py
movva_salesforce_tools/salesforce/marketing_cloud/mobile_connect.py
movva_salesforce_tools/salesforce/transational_sms/__init__.py
movva_salesforce_tools/salesforce/transational_sms/callback.py
movva_salesforce_tools/salesforce/utils.py
movva_salesforce_tools-0.2.7.dist-info/METADATA
movva_salesforce_tools-0.2.7.dist-info/WHEEL
movva_salesforce_tools-0.2.7.dist-info/RECORD
