Metadata-Version: 2.1
Name: movva-salesforce-tools
Version: 0.2.7
Summary: Pacote com ferramentas de integração com a salesforce
Author: WillamesCampos
Author-email: willwjccampos@gmail.com
Requires-Python: >=3.10,<4.0
Classifier: Programming Language :: Python :: 3
Classifier: Programming Language :: Python :: 3.10
Classifier: Programming Language :: Python :: 3.11
Requires-Dist: google-cloud (>=0.34.0,<0.35.0)
Requires-Dist: google-cloud-firestore (>=2.13.1,<3.0.0)
Requires-Dist: requests (>=2.31.0,<3.0.0)
